pynecone/.templates/apps/counter/__init__.py
pynecone/.templates/apps/counter/counter.py
pynecone/.templates/apps/default/__init__.py
pynecone/.templates/apps/default/default.py
pynecone/.templates/assets/favicon.ico
pynecone/.templates/jinja/app/pcconfig.py.jinja2
pynecone/.templates/jinja/web/pages/_document.js.jinja2
pynecone/.templates/jinja/web/pages/base_page.js.jinja2
pynecone/.templates/jinja/web/pages/custom_component.js.jinja2
pynecone/.templates/jinja/web/pages/index.js.jinja2
pynecone/.templates/jinja/web/pages/utils.js.jinja2
pynecone/.templates/jinja/web/utils/theme.js.jinja2
pynecone/.templates/web/.gitignore
pynecone/.templates/web/bun.lockb
pynecone/.templates/web/jsconfig.json
pynecone/.templates/web/next.config.js
pynecone/.templates/web/package.json
pynecone/.templates/web/pages/404.js
pynecone/.templates/web/pages/_app.js
pynecone/.templates/web/styles/code/prism.js
pynecone/.templates/web/utils/state.js
pynecone/__init__.py
pynecone/admin.py
pynecone/app.py
pynecone/base.py
pynecone/compiler/__init__.py
pynecone/compiler/compiler.py
pynecone/compiler/templates.py
pynecone/compiler/utils.py
pynecone/components/__init__.py
pynecone/components/base/__init__.py
pynecone/components/base/bare.py
pynecone/components/base/body.py
pynecone/components/base/document.py
pynecone/components/base/head.py
pynecone/components/base/link.py
pynecone/components/base/meta.py
pynecone/components/component.py
pynecone/components/datadisplay/__init__.py
pynecone/components/datadisplay/badge.py
pynecone/components/datadisplay/code.py
pynecone/components/datadisplay/datatable.py
pynecone/components/datadisplay/divider.py
pynecone/components/datadisplay/keyboard_key.py
pynecone/components/datadisplay/list.py
pynecone/components/datadisplay/stat.py
pynecone/components/datadisplay/table.py
pynecone/components/datadisplay/tag.py
pynecone/components/disclosure/__init__.py
pynecone/components/disclosure/accordion.py
pynecone/components/disclosure/tabs.py
pynecone-0.1.33.dist-info/LICENSE
pynecone-0.1.33.dist-info/METADATA
pynecone-0.1.33.dist-info/WHEEL
pynecone-0.1.33.dist-info/entry_points.txt
pynecone-0.1.33.dist-info/RECORD
