Metadata-Version: 2.1
Name: pynecone
Version: 0.1.33
Summary: Web apps in pure Python.
Home-page: https://pynecone.io
License: Apache-2.0
Keywords: web,framework
Author: Nikhil Rao
Author-email: nikhil@pynecone.io
Requires-Python: >=3.7,<4.0
Classifier: Development Status :: 4 - Beta
Classifier: License :: OSI Approved :: Apache Software License
Classifier: Programming Language :: Python :: 3
Classifier: Programming Language :: Python :: 3.7
Classifier: Programming Language :: Python :: 3.8
Classifier: Programming Language :: Python :: 3.9
Classifier: Programming Language :: Python :: 3.10
Classifier: Programming Language :: Python :: 3.11
Requires-Dist: cloudpickle (>=2.2.1,<3.0.0)
Requires-Dist: fastapi (>=0.96.0,<0.97.0)
Requires-Dist: gunicorn (>=20.1.0,<21.0.0)
Requires-Dist: httpx (>=0.23.0,<0.24.0)
Requires-Dist: jinja2 (>=3.1.2,<4.0.0)
Requires-Dist: plotly (>=5.13.0,<6.0.0)
Requires-Dist: psutil (>=5.9.4,<6.0.0)
Requires-Dist: pydantic (>=1.10.2,<2.0.0)
Requires-Dist: python-dotenv (>=0.13.0,<0.14.0)
Requires-Dist: python-multipart (>=0.0.5,<0.0.6)
Requires-Dist: python-socketio (>=5.7.0,<6.0.0)
Requires-Dist: redis (>=4.3.5,<5.0.0)
Requires-Dist: rich (>=13.0.0,<14.0.0)
Requires-Dist: sqlmodel (>=0.0.8,<0.0.9)
Requires-Dist: starlette-admin (>=0.9.0,<0.10.0)
Requires-Dist: typer (==0.4.2)
Requires-Dist: uvicorn (>=0.20.0,<0.21.0)
Requires-Dist: watchdog (>=2.3.1,<3.0.0)
Requires-Dist: websockets (>=10.4,<11.0)
Project-URL: Documentation, https://pynecone.io/docs/getting-started/introduction
Project-URL: Repository, https://github.com/pynecone-io/pynecone
